[
    {
        "thread_id": 16,
        "thread_post": "testing",
        "lastpostTime": "2022-03-02 05:48:36",
        "post_character_id": 1,
        "open": 1,
        "userID": 9,
        "lastpostUser": "neoixan",
        "topic_title": "Team Snagem HQ (Mt. Silver)"
    },
    {
        "thread_id": 51,
        "thread_post": "new team test",
        "lastpostTime": "2022-03-24 04:49:55",
        "post_character_id": 1,
        "open": 1,
        "userID": 9,
        "lastpostUser": "neoixan",
        "topic_title": "Team Snagem HQ (Mt. Silver)"
    },
    {
        "thread_id": 52,
        "thread_post": "kkk",
        "lastpostTime": "2022-03-24 04:54:36",
        "post_character_id": 2,
        "open": 1,
        "userID": 9,
        "lastpostUser": "neoixan",
        "topic_title": "Team Snagem HQ (Mt. Silver)"
    },
    {
        "thread_id": 56,
        "thread_post": "Here we are gonna test",
        "lastpostTime": "2022-04-11 11:19:11",
        "post_character_id": 1,
        "open": 1,
        "userID": 9,
        "lastpostUser": "neoixan",
        "topic_title": "Team Snagem HQ (Mt. Silver)"
    },
    {
        "thread_id": 57,
        "thread_post": "dasdasd",
        "lastpostTime": "2022-04-12 12:47:36",
        "post_character_id": 1,
        "open": 1,
        "userID": 9,
        "lastpostUser": "neoixan",
        "topic_title": "Team Snagem HQ (Mt. Silver)"
    },
    {
        "thread_id": 58,
        "thread_post": "<h3><span style=\"color: rgb(224, 62, 45);\">A new mission!!</span></h3>\n<p>How are you guys??</p>\n<p><img src=\"https://via.placeholder.com/150\" alt=\"stuff\" width=\"150\" height=\"150\"> YES!</p>\n<p>here we go</p>",
        "lastpostTime": "2022-04-12 07:55:50",
        "post_character_id": 1,
        "open": 1,
        "userID": 9,
        "lastpostUser": "neoixan",
        "topic_title": "Team Snagem HQ (Mt. Silver)"
    },
    {
        "thread_id": 59,
        "thread_post": "<p style=\"text-align: left;\">left text test and&nbsp;</p>\n<p style=\"text-align: right;\">rgith</p>",
        "lastpostTime": "2022-04-12 08:07:26",
        "post_character_id": 1,
        "open": 1,
        "userID": 9,
        "lastpostUser": "neoixan",
        "topic_title": "Team Snagem HQ (Mt. Silver)"
    },
    {
        "thread_id": 62,
        "thread_post": "<p><span style=\"color: rgb(241, 196, 15);\">test</span></p>",
        "lastpostTime": "2022-04-14 03:18:08",
        "post_character_id": 2,
        "open": 1,
        "userID": 9,
        "lastpostUser": "neoixan",
        "topic_title": "Team Snagem HQ (Mt. Silver)"
    },
    {
        "thread_id": 64,
        "thread_post": "<p>Oh yes ?</p>",
        "lastpostTime": "2022-04-21 02:54:50",
        "post_character_id": 2,
        "open": 1,
        "userID": 9,
        "lastpostUser": "neoixan",
        "topic_title": "Team Snagem HQ (Mt. Silver)"
    },
    {
        "thread_id": 65,
        "thread_post": "<p>YES!</p>",
        "lastpostTime": "2022-04-21 02:55:25",
        "post_character_id": 1,
        "open": 1,
        "userID": 9,
        "lastpostUser": "neoixan",
        "topic_title": "Team Snagem HQ (Mt. Silver)"
    },
    {
        "thread_id": 66,
        "thread_post": "<p>:C</p>",
        "lastpostTime": "2022-04-21 02:55:33",
        "post_character_id": 2,
        "open": 1,
        "userID": 9,
        "lastpostUser": "neoixan",
        "topic_title": "Team Snagem HQ (Mt. Silver)"
    }
]